flask_wtf_polyglot/__init__.py
flask_wtf_polyglot/form.py
flask_wtf_polyglot-0.4.0.dist-info/LICENSE
flask_wtf_polyglot-0.4.0.dist-info/METADATA
flask_wtf_polyglot-0.4.0.dist-info/WHEEL
flask_wtf_polyglot-0.4.0.dist-info/RECORD
