Metadata-Version: 2.1
Name: flask-wtf-polyglot
Version: 0.4.0
Summary: Flask-WTF companion library for rendering polyglot HTML output
Home-page: https://gitlab.com/obda/flask-wtf-polyglot
License: BSD-3-Clause
Author: Clemens Kaposi
Author-email: clemens@kaposi.name
Requires-Python: >=3.7,<4.0
Classifier: Development Status :: 4 - Beta
Classifier: Environment :: Web Environment
Classifier: Intended Audience :: Developers
Classifier: License :: OSI Approved :: BSD License
Classifier: Operating System :: OS Independent
Classifier: Programming Language :: Python
Classifier: Programming Language :: Python :: 3
Classifier: Programming Language :: Python :: 3.7
Classifier: Programming Language :: Python :: 3.8
Classifier: Programming Language :: Python :: 3.9
Classifier: Programming Language :: Python :: 3.10
Classifier: Programming Language :: Python :: 3.11
Classifier: Programming Language :: Python :: 3
Classifier: Programming Language :: Python :: 3.10
Classifier: Programming Language :: Python :: 3.11
Classifier: Programming Language :: Python :: 3.7
Classifier: Programming Language :: Python :: 3.8
Classifier: Programming Language :: Python :: 3.9
Classifier: Topic :: Internet :: WWW/HTTP :: Dynamic Content
Classifier: Topic :: Software Development :: Libraries :: Python Modules
Requires-Dist: flask-wtf (>=1.1.1,<2.0.0)
Requires-Dist: wtforms-polyglot (>=0.4.0,<0.5.0)
Project-URL: Repository, https://gitlab.com/obda/flask-wtf-polyglot
